aws_cdk/zip_asset_code/__init__.py
build/lib/aws_cdk/zip_asset_code/__init__.py
build/lib/build/lib/aws_cdk/zip_asset_code/__init__.py
build/lib/build/lib/build/lib/aws_cdk/zip_asset_code/__init__.py
build/lib/build/lib/build/lib/build/lib/aws_cdk/zip_asset_code/__init__.py
build/lib/build/lib/build/lib/build/lib/build/lib/aws_cdk/zip_asset_code/__init__.py
build/lib/build/lib/build/lib/build/lib/build/lib/build/lib/aws_cdk/zip_asset_code/__init__.py
build/lib/build/lib/build/lib/build/lib/build/lib/build/lib/examples/example-cdk-lambda.py
build/lib/build/lib/build/lib/build/lib/build/lib/build/lib/examples/example-lambda/handler.py
build/lib/build/lib/build/lib/build/lib/build/lib/build/lib/examples/example-lambda/setup.py
build/lib/build/lib/build/lib/build/lib/build/lib/build/lib/examples/example-lambda/dist/site-packages/handler.py
build/lib/build/lib/build/lib/build/lib/build/lib/examples/example-cdk-lambda.py
build/lib/build/lib/build/lib/build/lib/build/lib/examples/example-lambda/handler.py
build/lib/build/lib/build/lib/build/lib/build/lib/examples/example-lambda/setup.py
build/lib/build/lib/build/lib/build/lib/build/lib/examples/example-lambda/dist/site-packages/handler.py
build/lib/build/lib/build/lib/build/lib/examples/example-cdk-lambda.py
build/lib/build/lib/build/lib/build/lib/examples/example-lambda/handler.py
build/lib/build/lib/build/lib/build/lib/examples/example-lambda/setup.py
build/lib/build/lib/build/lib/build/lib/examples/example-lambda/dist/site-packages/handler.py
build/lib/build/lib/build/lib/examples/example-cdk-lambda.py
build/lib/build/lib/build/lib/examples/example-lambda/handler.py
build/lib/build/lib/build/lib/examples/example-lambda/setup.py
build/lib/build/lib/build/lib/examples/example-lambda/dist/site-packages/handler.py
build/lib/build/lib/examples/example-cdk-lambda.py
build/lib/build/lib/examples/example-lambda/handler.py
build/lib/build/lib/examples/example-lambda/setup.py
aws_cdk.zip_asset_code-1.0.1.dist-info/METADATA
aws_cdk.zip_asset_code-1.0.1.dist-info/WHEEL
aws_cdk.zip_asset_code-1.0.1.dist-info/top_level.txt
aws_cdk.zip_asset_code-1.0.1.dist-info/RECORD
