Metadata-Version: 2.1
Name: aws-cdk.zip-asset-code
Version: 1.0.1
Summary: AWS CDK extension for aws-cdk.aws-lambda
Home-page: UNKNOWN
License: UNKNOWN
Platform: UNKNOWN
Requires-Python: >=3.8
Requires-Dist: aws-cdk.aws-lambda
